mcp_shell_server/__init__.py
mcp_shell_server/command_preprocessor.py
mcp_shell_server/command_validator.py
mcp_shell_server/directory_manager.py
mcp_shell_server/io_redirection_handler.py
mcp_shell_server/process_manager.py
mcp_shell_server/server.py
mcp_shell_server/shell_executor.py
mcp_shell_server/version.py
mcp_shell_server_fastmcp-0.0.0.dev0.dist-info/METADATA
mcp_shell_server_fastmcp-0.0.0.dev0.dist-info/WHEEL
mcp_shell_server_fastmcp-0.0.0.dev0.dist-info/entry_points.txt
mcp_shell_server_fastmcp-0.0.0.dev0.dist-info/licenses/LICENSE
mcp_shell_server_fastmcp-0.0.0.dev0.dist-info/RECORD
